nexium_database/__init__.py
nexium_database/database/__init__.py
nexium_database/database/database.py
nexium_database/models/__init__.py
nexium_database/models/base.py
nexium_database/repositories/__init__.py
nexium_database/repositories/base.py
nexium_database/utils/__init__.py
nexium_database/utils/exceptions.py
tests/__init__.py
tests/main.py
tests/database/__init__.py
tests/database/database.py
tests/models/__init__.py
tests/models/user.py
tests/repositories/__init__.py
tests/repositories/user.py
nexium_database-0.1.2.dist-info/LICENSE
nexium_database-0.1.2.dist-info/METADATA
nexium_database-0.1.2.dist-info/WHEEL
nexium_database-0.1.2.dist-info/top_level.txt
nexium_database-0.1.2.dist-info/RECORD
